papercli/__init__.py
papercli/__main__.py
papercli/api.py
papercli/papercli.py
papercli/save.py
papercli/textgen.py
paper_cli-0.2.3.dist-info/METADATA
paper_cli-0.2.3.dist-info/WHEEL
paper_cli-0.2.3.dist-info/entry_points.txt
paper_cli-0.2.3.dist-info/top_level.txt
paper_cli-0.2.3.dist-info/RECORD
